comfort/__init__.py
comfort/comfort.py
comfort-1.0.2.dist-info/DESCRIPTION.rst
comfort-1.0.2.dist-info/METADATA
comfort-1.0.2.dist-info/RECORD
comfort-1.0.2.dist-info/WHEEL
comfort-1.0.2.dist-info/metadata.json
comfort-1.0.2.dist-info/top_level.txt
src/__init__.py
src/comfort.py
