Metadata-Version: 2.0
Name: comfort
Version: 1.0.2
Summary: Compute basic thermal comfort indices
Home-page: https://github.com/sprite728/comfort
Author: Chuan-Che (Jeff) Huang
Author-email: chuanche@umich.edu
License: MIT
Keywords: comfort
Platform: UNKNOWN
Classifier: Development Status :: 3 - Alpha
Classifier: Intended Audience :: Science/Research
Classifier: Topic :: Scientific/Engineering
Classifier: License :: OSI Approved :: MIT License
Classifier: Programming Language :: Python :: 2.7
Classifier: Programming Language :: Python :: 3.4
Classifier: Programming Language :: Python :: 3.5
Classifier: Programming Language :: Python :: 3.6
